Workbook

Sheet Assumptions
A1: MICRON TECHNOLOGY INC (MU) — Valuation Assumptions
A2: Editable inputs on this tab. Fundamentals from SEC EDGAR; market/assumptions flagged.
A4: Tax rate [ASSUMPTION] | B4: 0.21
A5: Risk-free rate [ASSUMPTION] | B5: 0.043
A6: Equity risk premium [ASSUMPTION] | B6: 0.05
A7: Beta | B7: 2
A8: Pre-tax cost of debt [ASSUMPTION] | B8: 0.05
A9: Share price (USD) | B9: 1133.99
A10: Shares outstanding (m) | B10: 1125
A11: Terminal growth [ASSUMPTION] | B11: 0.025
A12: D&A (% revenue) | B12: 0.285
A13: Capex (% revenue) | B13: 0.3447
A14: Incr. NWC (% of rev change) [ASSUMPTION] | B14: 0.05
A15: Total debt ($m) — EDGAR | B15: 12093
A16: Cash ($m) — EDGAR | B16: 9642
A18: Revenue growth Yr1–Yr5 [ASSUMPTION]
A19: growth Yr1 | B19: 0.0671
A20: growth Yr2 | B20: 0.0566
A21: growth Yr3 | B21: 0.0461
A22: growth Yr4 | B22: 0.0355
A23: growth Yr5 | B23: 0.025
A25: EBIT margin Yr1–Yr5 [ASSUMPTION]
A26: margin Yr1 | B26: 0.1382
A27: margin Yr2 | B27: 0.1382
A28: margin Yr3 | B28: 0.1382
A29: margin Yr4 | B29: 0.1382
A30: margin Yr5 | B30: 0.1382

Sheet Model
A1: MU — Income statement & FCFF ($m)
B3: FY2022 | C3: FY2023 | D3: FY2024 | E3: FY2025 | F3: Yr1 | G3: Yr2 | H3: Yr3 | I3: Yr4 | J3: Yr5
A4: Revenue ($m) | B4: 30758 | C4: 15540 | D4: 25111 | E4: 37378 | F4: =E4*(1+Assumptions!B19) | G4: =F4*(1+Assumptions!B20) | H4: =G4*(1+Assumptions!B21) | I4: =H4*(1+Assumptions!B22) | J4: =I4*(1+Assumptions!B23)
A5: Operating income / EBIT ($m) | B5: 9702 | C5: -5745 | D5: 1304 | E5: 9770 | F5: =F4*Assumptions!B26 | G5: =G4*Assumptions!B27 | H5: =H4*Assumptions!B28 | I5: =I4*Assumptions!B29 | J5: =J4*Assumptions!B30
A6: EBIT margin (%) | B6: =B5/B4 | C6: =C5/C4 | D6: =D5/D4 | E6: =E5/E4 | F6: =F5/F4 | G6: =G5/G4 | H6: =H5/H4 | I6: =I5/I4 | J6: =J5/J4
A7: Net income ($m) | B7: 8687 | C7: -5833 | D7: 778 | E7: 8539
A8: EPS diluted ($) | B8: 7.75 | C8: -5.34 | D8: 0.7 | E8: 7.59
A10: Free cash flow to firm (projection)
A11: NOPAT ($m) | F11: =F5*(1-Assumptions!B4) | G11: =G5*(1-Assumptions!B4) | H11: =H5*(1-Assumptions!B4) | I11: =I5*(1-Assumptions!B4) | J11: =J5*(1-Assumptions!B4)
A12: D&A ($m) | F12: =F4*Assumptions!B12 | G12: =G4*Assumptions!B12 | H12: =H4*Assumptions!B12 | I12: =I4*Assumptions!B12 | J12: =J4*Assumptions!B12
A13: Capex ($m) | F13: =F4*Assumptions!B13 | G13: =G4*Assumptions!B13 | H13: =H4*Assumptions!B13 | I13: =I4*Assumptions!B13 | J13: =J4*Assumptions!B13
A14: Incr. NWC ($m) | F14: =(F4-E4)*Assumptions!B14 | G14: =(G4-F4)*Assumptions!B14 | H14: =(H4-G4)*Assumptions!B14 | I14: =(I4-H4)*Assumptions!B14 | J14: =(J4-I4)*Assumptions!B14
A15: FCFF ($m) | F15: =F11+F12-F13-F14 | G15: =G11+G12-G13-G14 | H15: =H11+H12-H13-H14 | I15: =I11+I12-I13-I14 | J15: =J11+J12-J13-J14

Sheet WACC
A1: WACC build
A4: Cost of equity (CAPM) | B4: =Assumptions!B5+Assumptions!B7*Assumptions!B6
A5: After-tax cost of debt | B5: =Assumptions!B8*(1-Assumptions!B4)
A6: Equity value ($m) | B6: =Assumptions!B9*Assumptions!B10
A7: Debt value ($m) | B7: =Assumptions!B15
A8: Equity weight | B8: =B6/(B6+B7)
A9: Debt weight | B9: =B7/(B6+B7)
A10: WACC | B10: =B8*B4+B9*B5

Sheet DCF
A1: Discounted cash flow (FCFF)
A3: Year | B3: 1 | C3: 2 | D3: 3 | E3: 4 | F3: 5
A4: FCFF ($m) | B4: =Model!F15 | C4: =Model!G15 | D4: =Model!H15 | E4: =Model!I15 | F4: =Model!J15
A5: Discount factor | B5: =1/(1+WACC!$B$10)^B3 | C5: =1/(1+WACC!$B$10)^C3 | D5: =1/(1+WACC!$B$10)^D3 | E5: =1/(1+WACC!$B$10)^E3 | F5: =1/(1+WACC!$B$10)^F3
A6: PV of FCFF ($m) | B6: =B4*B5 | C6: =C4*C5 | D6: =D4*D5 | E6: =E4*E5 | F6: =F4*F5
A8: Sum PV of FCFF ($m) | B8: =SUM(B6:F6)
A9: Terminal value ($m) | B9: =F4*(1+Assumptions!B11)/(WACC!B10-Assumptions!B11)
A10: PV of terminal value ($m) | B10: =B9*F5
A11: Enterprise value ($m) | B11: =B8+B10
A12: Less: net debt ($m) | B12: =Assumptions!B15-Assumptions!B16
A13: Equity value ($m) | B13: =B11-B12
A14: Shares (m) | B14: =Assumptions!B10
A15: Value per share ($) | B15: =B13/B14
A16: TV as % of EV | B16: =B10/B11

Sheet Sensitivity
A1: Value per share — WACC (rows) × terminal growth (cols)
B3: WACC\g | C3: 0.015 | D3: 0.02 | E3: 0.025 | F3: 0.03 | G3: 0.035
B4: =WACC!$B$10-0.015 | C4: =(SUMPRODUCT(DCF!$B$4:$F$4,1/(1+$B4)^DCF!$B$3:$F$3)+(DCF!$F$4*(1+C$3)/($B4-C$3))/(1+$B4)^5-(Assumptions!B15-Assumptions!B16))/Assumptions!B10 | D4: =(SUMPRODUCT(DCF!$B$4:$F$4,1/(1+$B4)^DCF!$B$3:$F$3)+(DCF!$F$4*(1+D$3)/($B4-D$3))/(1+$B4)^5-(Assumptions!B15-Assumptions!B16))/Assumptions!B10 | E4: =(SUMPRODUCT(DCF!$B$4:$F$4,1/(1+$B4)^DCF!$B$3:$F$3)+(DCF!$F$4*(1+E$3)/($B4-E$3))/(1+$B4)^5-(Assumptions!B15-Assumptions!B16))/Assumptions!B10 | F4: =(SUMPRODUCT(DCF!$B$4:$F$4,1/(1+$B4)^DCF!$B$3:$F$3)+(DCF!$F$4*(1+F$3)/($B4-F$3))/(1+$B4)^5-(Assumptions!B15-Assumptions!B16))/Assumptions!B10 | G4: =(SUMPRODUCT(DCF!$B$4:$F$4,1/(1+$B4)^DCF!$B$3:$F$3)+(DCF!$F$4*(1+G$3)/($B4-G$3))/(1+$B4)^5-(Assumptions!B15-Assumptions!B16))/Assumptions!B10
B5: =WACC!$B$10-0.0075 | C5: =(SUMPRODUCT(DCF!$B$4:$F$4,1/(1+$B5)^DCF!$B$3:$F$3)+(DCF!$F$4*(1+C$3)/($B5-C$3))/(1+$B5)^5-(Assumptions!B15-Assumptions!B16))/Assumptions!B10 | D5: =(SUMPRODUCT(DCF!$B$4:$F$4,1/(1+$B5)^DCF!$B$3:$F$3)+(DCF!$F$4*(1+D$3)/($B5-D$3))/(1+$B5)^5-(Assumptions!B15-Assumptions!B16))/Assumptions!B10 | E5: =(SUMPRODUCT(DCF!$B$4:$F$4,1/(1+$B5)^DCF!$B$3:$F$3)+(DCF!$F$4*(1+E$3)/($B5-E$3))/(1+$B5)^5-(Assumptions!B15-Assumptions!B16))/Assumptions!B10 | F5: =(SUMPRODUCT(DCF!$B$4:$F$4,1/(1+$B5)^DCF!$B$3:$F$3)+(DCF!$F$4*(1+F$3)/($B5-F$3))/(1+$B5)^5-(Assumptions!B15-Assumptions!B16))/Assumptions!B10 | G5: =(SUMPRODUCT(DCF!$B$4:$F$4,1/(1+$B5)^DCF!$B$3:$F$3)+(DCF!$F$4*(1+G$3)/($B5-G$3))/(1+$B5)^5-(Assumptions!B15-Assumptions!B16))/Assumptions!B10
B6: =WACC!$B$10 | C6: =(SUMPRODUCT(DCF!$B$4:$F$4,1/(1+$B6)^DCF!$B$3:$F$3)+(DCF!$F$4*(1+C$3)/($B6-C$3))/(1+$B6)^5-(Assumptions!B15-Assumptions!B16))/Assumptions!B10 | D6: =(SUMPRODUCT(DCF!$B$4:$F$4,1/(1+$B6)^DCF!$B$3:$F$3)+(DCF!$F$4*(1+D$3)/($B6-D$3))/(1+$B6)^5-(Assumptions!B15-Assumptions!B16))/Assumptions!B10 | E6: =(SUMPRODUCT(DCF!$B$4:$F$4,1/(1+$B6)^DCF!$B$3:$F$3)+(DCF!$F$4*(1+E$3)/($B6-E$3))/(1+$B6)^5-(Assumptions!B15-Assumptions!B16))/Assumptions!B10 | F6: =(SUMPRODUCT(DCF!$B$4:$F$4,1/(1+$B6)^DCF!$B$3:$F$3)+(DCF!$F$4*(1+F$3)/($B6-F$3))/(1+$B6)^5-(Assumptions!B15-Assumptions!B16))/Assumptions!B10 | G6: =(SUMPRODUCT(DCF!$B$4:$F$4,1/(1+$B6)^DCF!$B$3:$F$3)+(DCF!$F$4*(1+G$3)/($B6-G$3))/(1+$B6)^5-(Assumptions!B15-Assumptions!B16))/Assumptions!B10
B7: =WACC!$B$10+0.0075 | C7: =(SUMPRODUCT(DCF!$B$4:$F$4,1/(1+$B7)^DCF!$B$3:$F$3)+(DCF!$F$4*(1+C$3)/($B7-C$3))/(1+$B7)^5-(Assumptions!B15-Assumptions!B16))/Assumptions!B10 | D7: =(SUMPRODUCT(DCF!$B$4:$F$4,1/(1+$B7)^DCF!$B$3:$F$3)+(DCF!$F$4*(1+D$3)/($B7-D$3))/(1+$B7)^5-(Assumptions!B15-Assumptions!B16))/Assumptions!B10 | E7: =(SUMPRODUCT(DCF!$B$4:$F$4,1/(1+$B7)^DCF!$B$3:$F$3)+(DCF!$F$4*(1+E$3)/($B7-E$3))/(1+$B7)^5-(Assumptions!B15-Assumptions!B16))/Assumptions!B10 | F7: =(SUMPRODUCT(DCF!$B$4:$F$4,1/(1+$B7)^DCF!$B$3:$F$3)+(DCF!$F$4*(1+F$3)/($B7-F$3))/(1+$B7)^5-(Assumptions!B15-Assumptions!B16))/Assumptions!B10 | G7: =(SUMPRODUCT(DCF!$B$4:$F$4,1/(1+$B7)^DCF!$B$3:$F$3)+(DCF!$F$4*(1+G$3)/($B7-G$3))/(1+$B7)^5-(Assumptions!B15-Assumptions!B16))/Assumptions!B10
B8: =WACC!$B$10+0.015 | C8: =(SUMPRODUCT(DCF!$B$4:$F$4,1/(1+$B8)^DCF!$B$3:$F$3)+(DCF!$F$4*(1+C$3)/($B8-C$3))/(1+$B8)^5-(Assumptions!B15-Assumptions!B16))/Assumptions!B10 | D8: =(SUMPRODUCT(DCF!$B$4:$F$4,1/(1+$B8)^DCF!$B$3:$F$3)+(DCF!$F$4*(1+D$3)/($B8-D$3))/(1+$B8)^5-(Assumptions!B15-Assumptions!B16))/Assumptions!B10 | E8: =(SUMPRODUCT(DCF!$B$4:$F$4,1/(1+$B8)^DCF!$B$3:$F$3)+(DCF!$F$4*(1+E$3)/($B8-E$3))/(1+$B8)^5-(Assumptions!B15-Assumptions!B16))/Assumptions!B10 | F8: =(SUMPRODUCT(DCF!$B$4:$F$4,1/(1+$B8)^DCF!$B$3:$F$3)+(DCF!$F$4*(1+F$3)/($B8-F$3))/(1+$B8)^5-(Assumptions!B15-Assumptions!B16))/Assumptions!B10 | G8: =(SUMPRODUCT(DCF!$B$4:$F$4,1/(1+$B8)^DCF!$B$3:$F$3)+(DCF!$F$4*(1+G$3)/($B8-G$3))/(1+$B8)^5-(Assumptions!B15-Assumptions!B16))/Assumptions!B10

Sheet Comps
A1: Comparable-company valuation
A2: Peer multiples are ASSUMPTION inputs — replace with live peers.
A4: EBITDA ($m) | B4: 18122
A5: EV/EBITDA multiple (x) [ASSUMPTION] | B5: 12
A6: Implied EV ($m) | B6: =B4*B5
A7: Less: net debt ($m) | B7: =Assumptions!B15-Assumptions!B16
A8: Equity value ($m) | B8: =B6-B7
A9: Value/share — EV/EBITDA ($) | B9: =B8/Assumptions!B10
A11: EPS ($) | B11: 7.59
A12: P/E multiple (x) [ASSUMPTION] | B12: 18
A13: Value/share — P/E ($) | B13: =B11*B12
A14: Comps midpoint ($) | B14: =AVERAGE(B9,B13)
