Workbook

Sheet Assumptions
A1: Value-add deal — Assumptions (GBP)
A2: Edit these inputs and the Underwriting tab recalculates.
A4: Purchase price | B4: 10000000
A5: In-place NOI | B5: 600000
A6: Going-in cap rate | B6: 0.06
A7: Exit cap rate | B7: 0.0575
A8: Hold (years) | B8: 5
A9: NOI uplift (value-add) | B9: 0.3
A10: Stabilize (years) | B10: 2
A11: Post-stabilize NOI growth | B11: 0.03
A12: Renovation capex | B12: 1500000
A13: Acquisition costs (%) | B13: 0.02
A14: Selling costs (%) | B14: 0.015
A15: LTV | B15: 0.65
A16: Interest rate (IO) | B16: 0.065

Sheet Underwriting
A1: Underwriting (levered)
A3: Stabilized NOI | B3: =Assumptions!B5*(1+Assumptions!B9)
A4: Total cost | B4: =Assumptions!B4*(1+Assumptions!B13)+Assumptions!B12
A5: Loan | B5: =Assumptions!B15*Assumptions!B4
A6: Equity invested | B6: =B4-B5
A7: Debt service (IO) | B7: =B5*Assumptions!B16
A8: Debt yield | B8: =Assumptions!B5/B5
A9: LTC | B9: =B5/B4
A11: Year | B11: 0 | C11: 1 | D11: 2 | E11: 3 | F11: 4 | G11: 5
A12: NOI | C12: =IF(1<=Assumptions!B10,Assumptions!B5+($B$3-Assumptions!B5)*1/Assumptions!B10,$B$3*(1+Assumptions!B11)^(1-Assumptions!B10)) | D12: =IF(2<=Assumptions!B10,Assumptions!B5+($B$3-Assumptions!B5)*2/Assumptions!B10,$B$3*(1+Assumptions!B11)^(2-Assumptions!B10)) | E12: =IF(3<=Assumptions!B10,Assumptions!B5+($B$3-Assumptions!B5)*3/Assumptions!B10,$B$3*(1+Assumptions!B11)^(3-Assumptions!B10)) | F12: =IF(4<=Assumptions!B10,Assumptions!B5+($B$3-Assumptions!B5)*4/Assumptions!B10,$B$3*(1+Assumptions!B11)^(4-Assumptions!B10)) | G12: =IF(5<=Assumptions!B10,Assumptions!B5+($B$3-Assumptions!B5)*5/Assumptions!B10,$B$3*(1+Assumptions!B11)^(5-Assumptions!B10))
A13: DSCR | C13: =C12/$B$7 | D13: =D12/$B$7 | E13: =E12/$B$7 | F13: =F12/$B$7 | G13: =G12/$B$7
A14: Equity cash flow | B14: =-B6 | C14: =C12-$B$7 | D14: =D12-$B$7 | E14: =E12-$B$7 | F14: =F12-$B$7 | G14: =G12-$B$7+(($B$3*(1+Assumptions!B11)^(5+1-Assumptions!B10))/Assumptions!B7*(1-Assumptions!B14)-B5)
A16: Project IRR | B16: =IRR(B14:G14)
A17: Equity multiple | B17: =SUM(C14:G14)/B6

Sheet Waterfall
A1: LP / GP equity waterfall
A2: Tiers: 8%→GP 20% · 12%→GP 30% · 15%→GP 40%. Below first hurdle: LP 100% (capital + preferred).
A4: Year | B4: 0 | C4: 1 | D4: 2 | E4: 3 | F4: 4 | G4: 5
A5: Equity cash flow | B5: =Underwriting!B14 | C5: =Underwriting!C14 | D5: =Underwriting!D14 | E5: =Underwriting!E14 | F5: =Underwriting!F14 | G5: =Underwriting!G14
A6: LP distribution | B6: -5200000 | C6: 267500 | D6: 357500 | E6: 380900 | F6: 405002 | G6: 8232002.2
A7: GP promote | B7: 0 | C7: 0 | D7: 0 | E7: 0 | F7: 0 | G7: 736579.99
A8: Check (LP+GP−CF) | B8: =B6+B7-B5 | C8: =C6+C7-C5 | D8: =D6+D7-D5 | E8: =E6+E7-E5 | F8: =F6+F7-F5 | G8: =G6+G7-G5
A10: Project IRR | B10: =IRR(B5:G5)
A11: LP IRR | B11: =IRR(B6:G6)
A12: LP equity multiple | B12: =SUM(C6:G6)/-B6
A13: GP promote (total) | B13: =SUM(C7:G7)
A14: GP share of profit | B14: =B13/SUM(C5:G5)

Sheet Sensitivity
A1: LP IRR — exit cap (rows) × NOI uplift (cols)
A2: Computed by waterfall.py (LP IRR is iterative).
B3: exit\uplift | C3: 0.1 | D3: 0.2 | E3: 0.3 | F3: 0.4 | G3: 0.5
B4: 0.05 | C4: 0.1238 | D4: 0.1528 | E4: 0.1765 | F4: 0.1989 | G4: 0.2202
B5: 0.055 | C5: 0.0953 | D5: 0.1281 | E5: 0.1548 | F5: 0.177 | G5: 0.1982
B6: 0.0575 | C6: 0.0816 | D6: 0.1159 | E6: 0.144 | F6: 0.167 | G6: 0.1881
B7: 0.06 | C7: 0.0653 | D7: 0.103 | E7: 0.1328 | F7: 0.1574 | G7: 0.1785
B8: 0.065 | C8: 0.0329 | D8: 0.0782 | E8: 0.1108 | F8: 0.1379 | G8: 0.1606
