Workbook

Sheet Assumptions
A1: Micron (MU) — Valuation Assumptions
A2: Blue = input (editable). Figures sourced from SEC EDGAR unless flagged ASSUMPTION.
A4: Tax rate | B4: 0.13
A5: Risk-free rate | B5: 0.043
A6: Equity risk premium | B6: 0.05
A7: Beta [ASSUMPTION] | B7: 1.2
A8: Pre-tax cost of debt | B8: 0.05
A9: Share price (USD) [ASSUMPTION] | B9: 130
A10: Shares outstanding (m) | B10: 1125
A11: Terminal growth | B11: 0.025
A12: D&A (% revenue) | B12: 0.2234
A13: Capex (% revenue) [ASSUMPTION] | B13: 0.3
A14: Incr. NWC (% of rev change) [ASSUMPTION] | B14: 0.1
A15: Revenue growth Yr1-Yr5 [ASSUMPTION]
A16: growth Yr1 | B16: 0.22
A17: growth Yr2 | B17: 0.12
A18: growth Yr3 | B18: 0.08
A19: growth Yr4 | B19: 0.05
A20: growth Yr5 | B20: 0.04
A21: EBIT margin Yr1-Yr5 [ASSUMPTION]
A22: margin Yr1 | B22: 0.27
A23: margin Yr2 | B23: 0.28
A24: margin Yr3 | B24: 0.27
A25: margin Yr4 | B25: 0.26
A26: margin Yr5 | B26: 0.25
A28: LT debt FY2025 ($m) — EDGAR | B28: 11533
A29: Cash FY2025 ($m) — EDGAR | B29: 9642
A30: Base revenue FY2025 ($m) — EDGAR | B30: 37378

Sheet WACC
A1: WACC build
A4: Risk-free rate | B4: =Assumptions!B5
A5: Beta | B5: =Assumptions!B7
A6: Equity risk premium | B6: =Assumptions!B6
A7: Cost of equity | B7: =B4+B5*B6
A8: Pre-tax cost of debt | B8: =Assumptions!B8
A9: Tax rate | B9: =Assumptions!B4
A10: After-tax cost of debt | B10: =B8*(1-B9)
A11: Equity value ($m) | B11: =Assumptions!B9*Assumptions!B10
A12: Debt value ($m) | B12: =Assumptions!B28
A13: Equity weight | B13: =B11/(B11+B12)
A14: Debt weight | B14: =B12/(B11+B12)
A15: WACC | B15: =B13*B7+B14*B10

Sheet Model
A1: Micron (MU) — Income statement, FCFF, balance sheet & cash flow ($m)
B3: FY2022 | C3: FY2023 | D3: FY2024 | E3: FY2025 | F3: Yr1 | G3: Yr2 | H3: Yr3 | I3: Yr4 | J3: Yr5
A4: Revenue ($m) | B4: 30758 | C4: 15540 | D4: 25111 | E4: 37378 | F4: =E4*(1+Assumptions!B16) | G4: =F4*(1+Assumptions!B17) | H4: =G4*(1+Assumptions!B18) | I4: =H4*(1+Assumptions!B19) | J4: =I4*(1+Assumptions!B20)
A5: Gross profit ($m) | B5: 13898 | C5: -1416 | D5: 5613 | E5: 14873
A6: R&D ($m) | B6: 3116 | C6: 3114 | D6: 3430 | E6: 3798
A7: SG&A ($m) | B7: 1066 | C7: 920 | D7: 1129 | E7: 1205
A8: EBIT ($m) | B8: 9702 | C8: -5745 | D8: 1304 | E8: 9770 | F8: =F4*Assumptions!B22 | G8: =G4*Assumptions!B23 | H8: =H4*Assumptions!B24 | I8: =I4*Assumptions!B25 | J8: =J4*Assumptions!B26
A9: EBIT margin (%) | B9: =B8/B4 | C9: =C8/C4 | D9: =D8/D4 | E9: =E8/E4 | F9: =F8/F4 | G9: =G8/G4 | H9: =H8/H4 | I9: =I8/I4 | J9: =J8/J4
A10: Net income ($m) | B10: 8687 | C10: -5833 | D10: 778 | E10: 8539
A11: EPS diluted ($) | B11: 7.75 | C11: -5.34 | D11: 0.7 | E11: 7.59
A13: Free cash flow to firm (projection)
A14: NOPAT ($m) | F14: =F8*(1-Assumptions!B4) | G14: =G8*(1-Assumptions!B4) | H14: =H8*(1-Assumptions!B4) | I14: =I8*(1-Assumptions!B4) | J14: =J8*(1-Assumptions!B4)
A15: D&A ($m) | B15: 7116 | C15: 7756 | D15: 7780 | E15: 8352 | F15: =F4*Assumptions!B12 | G15: =G4*Assumptions!B12 | H15: =H4*Assumptions!B12 | I15: =I4*Assumptions!B12 | J15: =J4*Assumptions!B12
A16: Capex ($m) | B16: 12067 | C16: 7676 | D16: 8386 | E16: 15857 | F16: =F4*Assumptions!B13 | G16: =G4*Assumptions!B13 | H16: =H4*Assumptions!B13 | I16: =I4*Assumptions!B13 | J16: =J4*Assumptions!B13
A17: Incr. NWC ($m) | F17: =(F4-E4)*Assumptions!B14 | G17: =(G4-F4)*Assumptions!B14 | H17: =(H4-G4)*Assumptions!B14 | I17: =(I4-H4)*Assumptions!B14 | J17: =(J4-I4)*Assumptions!B14
A18: FCFF ($m) | F18: =F14+F15-F16-F17 | G18: =G14+G15-G16-G17 | H18: =H14+H15-H16-H17 | I18: =I14+I15-I16-I17 | J18: =J14+J15-J16-J17
A20: Balance sheet (FY actuals)
A21: Total assets ($m) | B21: 66283 | C21: 64254 | D21: 69416 | E21: 82798
A22: Cash & equivalents ($m) | B22: 8262 | C22: 8577 | D22: 7041 | E22: 9642
A23: Long-term debt ($m) | B23: 6020 | C23: 12049 | D23: 11343 | E23: 11533
A24: Stockholders' equity ($m) | B24: 49907 | C24: 44120 | D24: 45131 | E24: 54165
A26: Cash flow (FY actuals)
A27: Cash from operations ($m) | B27: 15181 | C27: 1559 | D27: 8507 | E27: 17525
A28: Capex ($m) | B28: 12067 | C28: 7676 | D28: 8386 | E28: 15857
A29: Free cash flow (CFO - capex) ($m) | B29: =B27-B28 | C29: =C27-C28 | D29: =D27-D28 | E29: =E27-E28

Sheet DCF
A1: Discounted cash flow (FCFF)
A3: Year | B3: 1 | C3: 2 | D3: 3 | E3: 4 | F3: 5
A4: FCFF ($m) | B4: =Model!F18 | C4: =Model!G18 | D4: =Model!H18 | E4: =Model!I18 | F4: =Model!J18
A5: Discount factor | B5: =1/(1+WACC!$B$15)^B3 | C5: =1/(1+WACC!$B$15)^C3 | D5: =1/(1+WACC!$B$15)^D3 | E5: =1/(1+WACC!$B$15)^E3 | F5: =1/(1+WACC!$B$15)^F3
A6: PV of FCFF ($m) | B6: =B4*B5 | C6: =C4*C5 | D6: =D4*D5 | E6: =E4*E5 | F6: =F4*F5
A8: Sum PV of FCFF ($m) | B8: =SUM(B6:F6)
A9: Terminal value ($m) | B9: =F4*(1+Assumptions!B11)/(WACC!B15-Assumptions!B11)
A10: PV of terminal value ($m) | B10: =B9*F5
A11: Enterprise value ($m) | B11: =B8+B10
A12: Less: net debt ($m) | B12: =Assumptions!B28-Assumptions!B29
A13: Equity value ($m) | B13: =B11-B12
A14: Shares (m) | B14: =Assumptions!B10
A15: Value per share ($) | B15: =B13/B14
A16: TV as % of EV | B16: =B10/B11

Sheet Sensitivity
A1: Value per share — WACC (rows) x terminal growth (cols)
B3: WACC \ g | C3: 0.015 | D3: 0.02 | E3: 0.025 | F3: 0.03 | G3: 0.035
B4: =WACC!$B$15-0.015 | C4: =(SUMPRODUCT(DCF!$B$4:$F$4,1/(1+$B4)^DCF!$B$3:$F$3)+(DCF!$F$4*(1+C$3)/($B4-C$3))/(1+$B4)^5-(Assumptions!$B$28-Assumptions!$B$29))/Assumptions!$B$10 | D4: =(SUMPRODUCT(DCF!$B$4:$F$4,1/(1+$B4)^DCF!$B$3:$F$3)+(DCF!$F$4*(1+D$3)/($B4-D$3))/(1+$B4)^5-(Assumptions!$B$28-Assumptions!$B$29))/Assumptions!$B$10 | E4: =(SUMPRODUCT(DCF!$B$4:$F$4,1/(1+$B4)^DCF!$B$3:$F$3)+(DCF!$F$4*(1+E$3)/($B4-E$3))/(1+$B4)^5-(Assumptions!$B$28-Assumptions!$B$29))/Assumptions!$B$10 | F4: =(SUMPRODUCT(DCF!$B$4:$F$4,1/(1+$B4)^DCF!$B$3:$F$3)+(DCF!$F$4*(1+F$3)/($B4-F$3))/(1+$B4)^5-(Assumptions!$B$28-Assumptions!$B$29))/Assumptions!$B$10 | G4: =(SUMPRODUCT(DCF!$B$4:$F$4,1/(1+$B4)^DCF!$B$3:$F$3)+(DCF!$F$4*(1+G$3)/($B4-G$3))/(1+$B4)^5-(Assumptions!$B$28-Assumptions!$B$29))/Assumptions!$B$10
B5: =WACC!$B$15-0.0075 | C5: =(SUMPRODUCT(DCF!$B$4:$F$4,1/(1+$B5)^DCF!$B$3:$F$3)+(DCF!$F$4*(1+C$3)/($B5-C$3))/(1+$B5)^5-(Assumptions!$B$28-Assumptions!$B$29))/Assumptions!$B$10 | D5: =(SUMPRODUCT(DCF!$B$4:$F$4,1/(1+$B5)^DCF!$B$3:$F$3)+(DCF!$F$4*(1+D$3)/($B5-D$3))/(1+$B5)^5-(Assumptions!$B$28-Assumptions!$B$29))/Assumptions!$B$10 | E5: =(SUMPRODUCT(DCF!$B$4:$F$4,1/(1+$B5)^DCF!$B$3:$F$3)+(DCF!$F$4*(1+E$3)/($B5-E$3))/(1+$B5)^5-(Assumptions!$B$28-Assumptions!$B$29))/Assumptions!$B$10 | F5: =(SUMPRODUCT(DCF!$B$4:$F$4,1/(1+$B5)^DCF!$B$3:$F$3)+(DCF!$F$4*(1+F$3)/($B5-F$3))/(1+$B5)^5-(Assumptions!$B$28-Assumptions!$B$29))/Assumptions!$B$10 | G5: =(SUMPRODUCT(DCF!$B$4:$F$4,1/(1+$B5)^DCF!$B$3:$F$3)+(DCF!$F$4*(1+G$3)/($B5-G$3))/(1+$B5)^5-(Assumptions!$B$28-Assumptions!$B$29))/Assumptions!$B$10
B6: =WACC!$B$15 | C6: =(SUMPRODUCT(DCF!$B$4:$F$4,1/(1+$B6)^DCF!$B$3:$F$3)+(DCF!$F$4*(1+C$3)/($B6-C$3))/(1+$B6)^5-(Assumptions!$B$28-Assumptions!$B$29))/Assumptions!$B$10 | D6: =(SUMPRODUCT(DCF!$B$4:$F$4,1/(1+$B6)^DCF!$B$3:$F$3)+(DCF!$F$4*(1+D$3)/($B6-D$3))/(1+$B6)^5-(Assumptions!$B$28-Assumptions!$B$29))/Assumptions!$B$10 | E6: =(SUMPRODUCT(DCF!$B$4:$F$4,1/(1+$B6)^DCF!$B$3:$F$3)+(DCF!$F$4*(1+E$3)/($B6-E$3))/(1+$B6)^5-(Assumptions!$B$28-Assumptions!$B$29))/Assumptions!$B$10 | F6: =(SUMPRODUCT(DCF!$B$4:$F$4,1/(1+$B6)^DCF!$B$3:$F$3)+(DCF!$F$4*(1+F$3)/($B6-F$3))/(1+$B6)^5-(Assumptions!$B$28-Assumptions!$B$29))/Assumptions!$B$10 | G6: =(SUMPRODUCT(DCF!$B$4:$F$4,1/(1+$B6)^DCF!$B$3:$F$3)+(DCF!$F$4*(1+G$3)/($B6-G$3))/(1+$B6)^5-(Assumptions!$B$28-Assumptions!$B$29))/Assumptions!$B$10
B7: =WACC!$B$15+0.0075 | C7: =(SUMPRODUCT(DCF!$B$4:$F$4,1/(1+$B7)^DCF!$B$3:$F$3)+(DCF!$F$4*(1+C$3)/($B7-C$3))/(1+$B7)^5-(Assumptions!$B$28-Assumptions!$B$29))/Assumptions!$B$10 | D7: =(SUMPRODUCT(DCF!$B$4:$F$4,1/(1+$B7)^DCF!$B$3:$F$3)+(DCF!$F$4*(1+D$3)/($B7-D$3))/(1+$B7)^5-(Assumptions!$B$28-Assumptions!$B$29))/Assumptions!$B$10 | E7: =(SUMPRODUCT(DCF!$B$4:$F$4,1/(1+$B7)^DCF!$B$3:$F$3)+(DCF!$F$4*(1+E$3)/($B7-E$3))/(1+$B7)^5-(Assumptions!$B$28-Assumptions!$B$29))/Assumptions!$B$10 | F7: =(SUMPRODUCT(DCF!$B$4:$F$4,1/(1+$B7)^DCF!$B$3:$F$3)+(DCF!$F$4*(1+F$3)/($B7-F$3))/(1+$B7)^5-(Assumptions!$B$28-Assumptions!$B$29))/Assumptions!$B$10 | G7: =(SUMPRODUCT(DCF!$B$4:$F$4,1/(1+$B7)^DCF!$B$3:$F$3)+(DCF!$F$4*(1+G$3)/($B7-G$3))/(1+$B7)^5-(Assumptions!$B$28-Assumptions!$B$29))/Assumptions!$B$10
B8: =WACC!$B$15+0.015 | C8: =(SUMPRODUCT(DCF!$B$4:$F$4,1/(1+$B8)^DCF!$B$3:$F$3)+(DCF!$F$4*(1+C$3)/($B8-C$3))/(1+$B8)^5-(Assumptions!$B$28-Assumptions!$B$29))/Assumptions!$B$10 | D8: =(SUMPRODUCT(DCF!$B$4:$F$4,1/(1+$B8)^DCF!$B$3:$F$3)+(DCF!$F$4*(1+D$3)/($B8-D$3))/(1+$B8)^5-(Assumptions!$B$28-Assumptions!$B$29))/Assumptions!$B$10 | E8: =(SUMPRODUCT(DCF!$B$4:$F$4,1/(1+$B8)^DCF!$B$3:$F$3)+(DCF!$F$4*(1+E$3)/($B8-E$3))/(1+$B8)^5-(Assumptions!$B$28-Assumptions!$B$29))/Assumptions!$B$10 | F8: =(SUMPRODUCT(DCF!$B$4:$F$4,1/(1+$B8)^DCF!$B$3:$F$3)+(DCF!$F$4*(1+F$3)/($B8-F$3))/(1+$B8)^5-(Assumptions!$B$28-Assumptions!$B$29))/Assumptions!$B$10 | G8: =(SUMPRODUCT(DCF!$B$4:$F$4,1/(1+$B8)^DCF!$B$3:$F$3)+(DCF!$F$4*(1+G$3)/($B8-G$3))/(1+$B8)^5-(Assumptions!$B$28-Assumptions!$B$29))/Assumptions!$B$10

Sheet Comps
A1: Comparable-company valuation
A2: Peer multiples are ASSUMPTION inputs (semis-sector typical) — replace with live peers.
A4: EBITDA FY2025 ($m) | B4: =Model!E8+Model!E15
A5: EV/EBITDA multiple (x) [ASSUMPTION] | B5: 8
A6: Implied EV ($m) | B6: =B4*B5
A7: Less: net debt ($m) | B7: =Assumptions!B28-Assumptions!B29
A8: Equity value ($m) | B8: =B6-B7
A9: Value/share — EV/EBITDA ($) | B9: =B8/Assumptions!B10
A11: EPS FY2025 ($) | B11: =Model!E11
A12: P/E multiple (x) [ASSUMPTION] | B12: 15
A13: Value/share — P/E ($) | B13: =B11*B12
A14: Comps midpoint ($) | B14: =AVERAGE(B9,B13)
